telegram_calendar/__init__.py
telegram_calendar/builder.py
telegram_calendar/calendar_types.py
telegram_calendar/callback.py
telegram_calendar/utils.py
telegram_calendar-0.4.0.dist-info/METADATA
telegram_calendar-0.4.0.dist-info/WHEEL
telegram_calendar-0.4.0.dist-info/top_level.txt
telegram_calendar-0.4.0.dist-info/RECORD
